dhis2/__init__.py
dhis2/__version__.py
dhis2/api.py
dhis2/exceptions.py
dhis2/logger.py
dhis2/utils.py
dhis2.py-2.3.0.dist-info/LICENSE
dhis2.py-2.3.0.dist-info/METADATA
dhis2.py-2.3.0.dist-info/WHEEL
dhis2.py-2.3.0.dist-info/top_level.txt
dhis2.py-2.3.0.dist-info/RECORD
