Metadata-Version: 2.1
Name: dhis2.py
Version: 2.3.0
Summary: Python wrapper for DHIS2
Home-page: https://github.com/davidhuser/dhis2.py
Author: David Huser
Author-email: dhuser@baosystems.com
License: MIT
Keywords: dhis2
Platform: UNKNOWN
Classifier: License :: OSI Approved :: MIT License
Classifier: Intended Audience :: Developers
Classifier: Development Status :: 5 - Production/Stable
Classifier: Programming Language :: Python
Classifier: Programming Language :: Python :: 3
Classifier: Programming Language :: Python :: 3.6
Classifier: Programming Language :: Python :: 3.7
Classifier: Programming Language :: Python :: 3.8
Requires-Python: >=3.6
License-File: LICENSE
